databot/PyDatabot.py
databot/__init__.py
databot_py-0.0.8.dist-info/LICENSE
databot_py-0.0.8.dist-info/METADATA
databot_py-0.0.8.dist-info/WHEEL
databot_py-0.0.8.dist-info/top_level.txt
databot_py-0.0.8.dist-info/RECORD
