Metadata-Version: 2.1
Name: databot-py
Version: 0.0.8
Summary: databot Python Library
Home-page: https://github.com/dbaldwin/databot-py
Author: Pat Ryan, Dennis Baldwin
Author-email: theyoungsoul@gmail.com, db@droneblocks.io
License: MIT
License-File: LICENSE
Requires-Dist: bleak ==0.21.1
